nonebot_plugin_maidle/__init__.py
nonebot_plugin_maidle/commands.py
nonebot_plugin_maidle/utils.py
nonebot_plugin_maidle/static/alias.json
nonebot_plugin_maidle/static/all_alias.json
nonebot_plugin_maidle/static/music_alias.json
nonebot_plugin_maidle/static/music_info.json
nonebot_plugin_maidle-0.0.6.dist-info/licenses/LICENSE
nonebot_plugin_maidle-0.0.6.dist-info/METADATA
nonebot_plugin_maidle-0.0.6.dist-info/WHEEL
nonebot_plugin_maidle-0.0.6.dist-info/top_level.txt
nonebot_plugin_maidle-0.0.6.dist-info/RECORD
