Metadata-Version: 2.4
Name: nonebot_plugin_maidle
Version: 0.0.6
Summary: 基于nonebot的maimai猜歌插件，支持多平台
Home-page: https://github.com/huanxin996/nonebot_plugin_maidle
Author: huanxin996
Author-email: mc.xiaolang@foxmail.com
Classifier: Programming Language :: Python :: 3
Classifier: License :: OSI Approved :: MIT License
Classifier: Operating System :: OS Independent
Requires-Python: >=3.8
License-File: LICENSE
Requires-Dist: nonebot2<3.0.0,>=2.3.0
Requires-Dist: nonebot_plugin_alconna>=0.54.0
Requires-Dist: nonebot_plugin_apscheduler<0.6.0,>=0.3.0
Requires-Dist: aiohttp>=3.0.0
Requires-Dist: pillow>=10.0.0
Dynamic: author
Dynamic: author-email
Dynamic: classifier
Dynamic: description
Dynamic: description-content-type
Dynamic: home-page
Dynamic: license-file
Dynamic: requires-dist
Dynamic: requires-python
Dynamic: summary
